Metadata-Version: 2.1
Name: pyscf-semiempirical
Version: 0.1.1
Summary: Semi-empirical methods for PySCF
Home-page: UNKNOWN
Author: Qiming Sun
Author-email: osirpt.sun@gmail.com
License: UNKNOWN
Platform: UNKNOWN
License-File: LICENSE
